MANIFEST.in
README.rst
setup.py
bin/make-deb
make_deb/__init__.py
make_deb.egg-info/PKG-INFO
make_deb.egg-info/SOURCES.txt
make_deb.egg-info/dependency_links.txt
make_deb.egg-info/not-zip-safe
make_deb.egg-info/pbr.json
make_deb.egg-info/requires.txt
make_deb.egg-info/top_level.txt
make_deb/resources/debian/changelog.j2
make_deb/resources/debian/compat.j2
make_deb/resources/debian/control.j2
make_deb/resources/debian/rules.j2
make_deb/resources/debian/triggers.j2