Metadata-Version: 1.0
Name: make-deb
Version: 0.0.5
Summary: Generates Debian configuration based on your setup.py
Home-page: UNKNOWN
Author: Nylas Team
Author-email: support@nylas.com
License: UNKNOWN
Platform: UNKNOWN
